fllm_cli-1.0.0.data/scripts/fllm
fllm_cli-1.0.0.data/scripts/fllm.bat
fllm_cli-1.0.0.data/scripts/fllm.completion.sh
fllm_cli-1.0.0.data/scripts/fllmps.ps1
foundationallm/__init__.py
foundationallm/cli/__init__.py
foundationallm/cli/__main__.py
foundationallm/cli/command_modules/__init__.py
foundationallm/cli/command_modules/cloud/__init__.py
foundationallm/cli/command_modules/cloud/_completers.py
foundationallm/cli/command_modules/cloud/_help.py
foundationallm/cli/command_modules/cloud/custom.py
foundationallm/cli/command_modules/extension/__init__.py
foundationallm/cli/command_modules/extension/_completers.py
foundationallm/cli/command_modules/extension/_help.py
foundationallm/cli/command_modules/extension/custom.py
foundationallm/cli/command_modules/fllm/__init__.py
foundationallm/cli/command_modules/fllm/_help.py
foundationallm/cli/command_modules/fllm/_params.py
foundationallm/cli/command_modules/fllm/commands.py
foundationallm/cli/command_modules/fllm/custom.py
foundationallm/cli/command_modules/fllm/aaz/__init__.py
foundationallm/cli/command_modules/fllm/aaz/latest/__init__.py
foundationallm/cli/command_modules/fllm/aaz/latest/configuration/__cmd_group.py
foundationallm/cli/command_modules/fllm/aaz/latest/configuration/__init__.py
foundationallm/cli/command_modules/fllm/aaz/latest/configuration/_delete.py
foundationallm/cli/command_modules/fllm/aaz/latest/configuration/_show.py
foundationallm/cli/command_modules/fllm/aaz/latest/configuration/_upsert_resource.py
foundationallm/cli/command_modules/fllm/aaz/latest/configuration/cache/__cmd_group.py
foundationallm/cli/command_modules/fllm/aaz/latest/configuration/cache/__init__.py
foundationallm/cli/command_modules/fllm/aaz/latest/configuration/cache/agent/__cmd_group.py
foundationallm/cli/command_modules/fllm/aaz/latest/configuration/cache/agent/__init__.py
foundationallm/cli/command_modules/fllm/aaz/latest/configuration/cache/agent/_clear.py
fllm_cli-1.0.0.dist-info/LICENSE.txt
fllm_cli-1.0.0.dist-info/METADATA
fllm_cli-1.0.0.dist-info/WHEEL
fllm_cli-1.0.0.dist-info/top_level.txt
fllm_cli-1.0.0.dist-info/RECORD
